fetchhtml/__init__.py
fetchhtml/fetchhtml.py
fetchhtml-0.6.dist-info/LICENSE
fetchhtml-0.6.dist-info/METADATA
fetchhtml-0.6.dist-info/WHEEL
fetchhtml-0.6.dist-info/top_level.txt
fetchhtml-0.6.dist-info/RECORD
