Metadata-Version: 2.1
Name: fetchhtml
Version: 0.6
Summary: UNKNOWN
Home-page: UNKNOWN
License: UNKNOWN
Platform: UNKNOWN
Requires-Dist: requests (>=2.23.0)
Requires-Dist: bs4 (>=0.0.1)
Requires-Dist: lxml
